{"summaries":[{"symbol":{"__symbol":0,"members":[]},"metadata":{"__symbolic":"new","expression":{"__symbol":1,"members":[]},"arguments":["CONFIG"]}},{"symbol":{"__symbol":2,"members":[]},"metadata":{"__symbolic":"interface"}}],"symbols":[{"__symbol":0,"name":"CONFIG","filePath":"/Users/dave/Development/Gyunu/ng-api/src/contracts/config.contract.d.ts"},{"__symbol":1,"name":"OpaqueToken","filePath":"/Users/dave/Development/Gyunu/ng-api/node_modules/@angular/core/core.d.ts"},{"__symbol":2,"name":"ApiConfig","filePath":"/Users/dave/Development/Gyunu/ng-api/src/contracts/config.contract.d.ts"}]}